blurry/__init__.py
blurry/__main__.py
blurry/async_typer.py
blurry/cli.py
blurry/commands/__init__.py
blurry/commands/clean.py
blurry/commands/init.py
blurry/commands/version.py
blurry/constants.py
blurry/file_processors/__init__.py
blurry/gather_file_data_by_directory.py
blurry/images.py
blurry/markdown/__init__.py
blurry/markdown/front_matter.py
blurry/markdown/renderer_functions/__init__.py
blurry/markdown/renderer_functions/render_video.py
blurry/open_graph.py
blurry/plugins/__init__.py
blurry/plugins/html_plugins/__init__.py
blurry/plugins/html_plugins/minify_html_plugin.py
blurry/plugins/jinja_plugins/__init__.py
blurry/plugins/jinja_plugins/blurry_image_extension.py
blurry/plugins/jinja_plugins/filters.py
blurry/plugins/markdown_plugins/__init__.py
blurry/plugins/markdown_plugins/container_plugin.py
blurry/plugins/markdown_plugins/punctuation_plugin.py
blurry/plugins/markdown_plugins/python_code_plugin.py
blurry/py.typed
blurry/runserver_handlers.py
blurry/schema_validation/__init__.py
blurry/schema_validation/models.py
blurry/settings.py
blurry/sitemap.py
blurry/templates.py
blurry/types.py
blurry/utils.py
blurry_cli-0.21.0.dist-info/METADATA
blurry_cli-0.21.0.dist-info/WHEEL
blurry_cli-0.21.0.dist-info/entry_points.txt
blurry_cli-0.21.0.dist-info/licenses/LICENSE
blurry_cli-0.21.0.dist-info/RECORD
