Metadata-Version: 2.4
Name: blurry-cli
Version: 0.21.0
Summary: A Mistune-based static site generator for Python
License: MIT
License-File: LICENSE
Keywords: static-site-generator,seo,pagespeed
Author: John Franey
Author-email: franey@duck.com
Requires-Python: >=3.11,<4.0
Classifier: Environment :: Console
Classifier: License :: OSI Approved :: MIT License
Classifier: Operating System :: OS Independent
Classifier: Programming Language :: Python :: 3
Classifier: Programming Language :: Python :: 3.11
Classifier: Programming Language :: Python :: 3.12
Classifier: Programming Language :: Python :: 3.13
Classifier: Programming Language :: Python :: 3.14
Classifier: Topic :: Internet :: WWW/HTTP :: Dynamic Content :: Content Management System
Classifier: Topic :: Internet :: WWW/HTTP :: Site Management
Classifier: Topic :: Software Development :: Libraries :: Python Modules
Classifier: Topic :: Text Processing :: Markup :: HTML
Classifier: Topic :: Text Processing :: Markup :: Markdown
Requires-Dist: Jinja2 (>=3.1.5,<4.0.0)
Requires-Dist: PyLD (>=2.0.4,<3.0.0)
Requires-Dist: dpath (>=2.2.0,<3.0.0)
Requires-Dist: htmlmin2 (>=0.1.13,<0.2.0)
Requires-Dist: jinja2-simple-tags (>=0.6.1,<0.7.0)
Requires-Dist: jinjax (>=0.48,<0.63)
Requires-Dist: livereload (>=2.7.1,<3.0.0)
Requires-Dist: mistune (>=3.1.0,<4.0.0)
Requires-Dist: pillow (>=12.0.0,<13.0.0)
Requires-Dist: pydantic (>=2.10.5,<3.0.0)
Requires-Dist: pymediainfo (>=7.0.1,<8.0.0)
Requires-Dist: rich (>=13.9.4,<15.0.0)
Requires-Dist: selectolax (>=0.3.27,<0.4.0)
Requires-Dist: typer (>=0.15.1,<0.21.0)
Project-URL: Repository, https://github.com/blurry-dev/blurry
